sphinx_a4doc/__init__.py
sphinx_a4doc/autodoc_directive.py
sphinx_a4doc/diagram_directive.py
sphinx_a4doc/domain.py
sphinx_a4doc/settings.py
sphinx_a4doc/_static/a4_railroad_diagram.css
sphinx_a4doc/_static/a4_railroad_diagram_latex.css
sphinx_a4doc/contrib/__init__.py
sphinx_a4doc/contrib/configurator.py
sphinx_a4doc/contrib/marker_nodes.py
sphinx_a4doc/contrib/railroad_diagrams.py
sphinx_a4doc/contrib/rst_autodoc.py
sphinx_a4doc/model/__init__.py
sphinx_a4doc/model/impl.py
sphinx_a4doc/model/model.py
sphinx_a4doc/model/model_renderer.py
sphinx_a4doc/model/reachable_finder.py
sphinx_a4doc/model/visitor.py
sphinx_a4doc/syntax/ANTLRv4Lexer.g4
sphinx_a4doc/syntax/ANTLRv4Lexer.tokens
sphinx_a4doc/syntax/ANTLRv4Parser.g4
sphinx_a4doc/syntax/LexBasic.g4
sphinx_a4doc/syntax/LexBasic.tokens
sphinx_a4doc/syntax/__init__.py
sphinx_a4doc/syntax/gen/__init__.py
sphinx_a4doc/syntax/gen/syntax/ANTLRv4Lexer.interp
sphinx_a4doc/syntax/gen/syntax/ANTLRv4Lexer.py
sphinx_a4doc/syntax/gen/syntax/ANTLRv4Lexer.tokens
sphinx_a4doc/syntax/gen/syntax/ANTLRv4Parser.interp
sphinx_a4doc/syntax/gen/syntax/ANTLRv4Parser.py
sphinx_a4doc/syntax/gen/syntax/ANTLRv4Parser.tokens
sphinx_a4doc/syntax/gen/syntax/ANTLRv4ParserListener.py
sphinx_a4doc/syntax/gen/syntax/ANTLRv4ParserVisitor.py
sphinx_a4doc/syntax/gen/syntax/LexerAdaptor.py
sphinx_a4doc/syntax/gen/syntax/__init__.py
sphinx_a4doc-1.7.0.dist-info/licenses/LICENSE
sphinx_a4doc-1.7.0.dist-info/METADATA
sphinx_a4doc-1.7.0.dist-info/WHEEL
sphinx_a4doc-1.7.0.dist-info/top_level.txt
sphinx_a4doc-1.7.0.dist-info/RECORD
