Metadata-Version: 2.4
Name: sphinx-a4doc
Version: 1.7.0
Summary: Sphinx domain and autodoc for Antlr4 grammars
Home-page: https://github.com/taminomara/sphinx-a4doc
Author: Tamika Nomara
Author-email: taminomara@gmail.com
License: MIT
Project-URL: Documentation, https://taminomara.github.io/sphinx-a4doc/
Project-URL: Source, https://github.com/taminomara/sphinx-a4doc
Project-URL: Tracker, https://github.com/taminomara/sphinx-a4doc/issues
Keywords: sphinx antlr4 autodoc
Classifier: Development Status :: 5 - Production/Stable
Classifier: Programming Language :: Python :: 3 :: Only
Classifier: Programming Language :: Python :: 3
Classifier: Programming Language :: Python :: 3.7
Classifier: Programming Language :: Python :: 3.8
Classifier: License :: OSI Approved :: MIT License
Classifier: Framework :: Sphinx
Classifier: Framework :: Sphinx :: Domain
Classifier: Framework :: Sphinx :: Extension
Classifier: Topic :: Software Development :: Documentation
Classifier: Topic :: Documentation
Classifier: Topic :: Documentation :: Sphinx
License-File: LICENSE
Requires-Dist: sphinx>=1.8.0
Requires-Dist: antlr4-python3-runtime~=4.13.2
Requires-Dist: PyYAML
Requires-Dist: svglib
Dynamic: license-file
Dynamic: project-url
